pge_plugin_terminal/__init__.py
pge_plugin_terminal/settings.py
pge_plugin_terminal/terminal_window.py
pge_plugin_terminal/models/__init__.py
pge_plugin_terminal/models/projects/__init__.py
pge_plugin_terminal/models/projects/projects_terminal.py
pge_plugin_terminal/resources/terminal.png
pge_plugin_terminal-0.1.dist-info/METADATA
pge_plugin_terminal-0.1.dist-info/RECORD
pge_plugin_terminal-0.1.dist-info/WHEEL
pge_plugin_terminal-0.1.dist-info/top_level.txt
