Metadata-Version: 2.1
Name: pge-plugin-terminal
Version: 0.1
Summary: Pyforms Generic Editor Terminal Plugin
Home-page: https://bitbucket.org/fchampalimaud/pycontrol-gui-plugin-terminal
Author: Ricardo Jorge Vieira Ribeiro
Author-email: ricardojvr@gmail.com
License: Copyright (C) 2007 Free Software Foundation, Inc. <http://fsf.org/>
Platform: UNKNOWN
